mup_xml_sign
