Metadata-Version: 2.1
Name: mup-xml-sign
Version: 0.1.1
Summary: mup-xml-sign
Home-page: http://github.com/SergeiPatiakin/mup-xml-sign
Author: Sergei Patiakin
Author-email: sergei.patiakin@gmail.com
License: Public Domain
Platform: UNKNOWN
Requires-Python: >=3.7
